shapleypy/__about__.py
shapleypy/__init__.py
shapleypy/_typing.py
shapleypy/classes_checkers.py
shapleypy/coalition.py
shapleypy/constants.py
shapleypy/game.py
shapleypy/generators.py
shapleypy/loaders.py
shapleypy/normalization.py
shapleypy/savers.py
shapleypy/solution_concept/__init__.py
shapleypy/solution_concept/_default_value.py
shapleypy/solution_concept/banzhaf_value.py
shapleypy/solution_concept/core.py
shapleypy/solution_concept/shapley_value.py
shapleypy-0.1.2.dist-info/METADATA
shapleypy-0.1.2.dist-info/WHEEL
shapleypy-0.1.2.dist-info/licenses/LICENSE
shapleypy-0.1.2.dist-info/RECORD
