Metadata-Version: 2.3
Name: shapleypy
Version: 0.1.2
Summary: Python library for cooperative game theory.
Project-URL: Documentation, https://github.com/muzikr/Shapleypy#readme
Project-URL: Issues, https://github.com/muzikr/Shapleypy/issues
Project-URL: Source, https://github.com/muzikr/Shapleypy
Author-email: Richard Muzik <richard@imuzik.cz>
License-Expression: GPL-3.0
License-File: LICENSE
Classifier: Development Status :: 4 - Beta
Classifier: Programming Language :: Python
Classifier: Programming Language :: Python :: 3.9
Classifier: Programming Language :: Python :: 3.10
Classifier: Programming Language :: Python :: 3.11
Classifier: Programming Language :: Python :: Implementation :: CPython
Classifier: Programming Language :: Python :: Implementation :: PyPy
Requires-Python: >=3.9
Requires-Dist: cysignals==1.11.4; platform_system != 'Windows'
Requires-Dist: gmpy2==2.1.5; platform_system != 'Windows'
Requires-Dist: numpy
Requires-Dist: pplpy==0.8.9; platform_system != 'Windows'
Requires-Dist: pyfmtools==0.81; platform_system == 'Linux'
